{
  "company": [
    {
      
      "data": [
        {
          "classification": "瀝青類",
          "number": "1-1",
          "productName": "馬歇爾試驗儀",
          "size": "1.機械式計數器、5.5lb、10lb可互換<br>2.12-18ln支落距、夯實接觸面積 2in圓形<br>3.符合CNS國家認證<br>4.電源110v/單相<br>5.馬力&frac12;hp<br>6.重量約90kg<br>7.尺寸700*450*120mm<br>備&emsp;&emsp;註：模具及相關配件需另選購",
          "image": "1-1",
          "filte": "1"
        },
{
"classification": "瀝青類",
          "number": "1-2",
          "productName": "穩定模4&quot",
          "size": "1.4ln模<br>2.馬歇爾專用模",
          "image": "1-2",
          "filte": "1"
        },
{
"classification": "瀝青類",
          "number": "1-3",
          "productName": "穩定模6&quot",
          "size": "1.6ln模<br>2.馬歇爾專用模",
          "image": "1-3",
          "filte": "1"
        },
{
"classification": "瀝青類",
          "number": "1-4",
          "productName": "間接張力4&quot",
          "size": "1.4ln-6ln 模<br>2.馬歇爾專用模<br>3.重量約4kg、5kg<br>4.尺寸約101.6mm-、152.4mm",
          "image": "1-4",
          "filte": "1"
        },
{
"classification": "瀝青類",
          "number": "1-5",
          "productName": "間接張力6&quot",
          "size": "1.4ln-6ln 模<br>2.馬歇爾專用模<br>3.重量約4kg、5kg<br>4.尺寸約101.6mm-、152.4mm",
          "image": "1-5",
          "filte": "1"
        },
{
"classification": "瀝青類",
          "number": "1-6",
          "productName": "瀝青延展性銅模",
          "size": "1.4ln-6ln 模<br>2.馬歇爾專用模",
          "image": "1-6",
          "filte": "1"
        },
{
"classification": "瀝青類",
          "number": "1-7",
          "productName": "電動瀝青油壓式頂樣器4&quotx6&quot",
          "size": "1.可調式0-75mm/min，頂樣圓盤及鋼模固定板4ln/6ln可互換<br>2.機台前後均設活動門片採電動開關、手離開關時自動提機模<br>3.加壓方式：油壓方式、頂樣時由上往下將樣品頂出<br>4.電源：220v/三相<br>5.馬力功率約750w<br>6.最大容量約4ton<br>7.尺寸約50*60*150 &plusmn;5cm",
          "image": "1-7",
          "filte": "1"
        },
{
"classification": "瀝青類",
          "number": "1-8",
          "productName": "變頻式瀝青洗油機3000g",
          "size": "1.轉速約3700rpm<br>2.符合:ASTM、AASHTO規範<br>3.電源:220v/60hz/單相/馬力1hp<br> 4.防爆型馬達重量約3000kg<br>5.尺寸約50*37*55cm",
          "image": "1-8",
          "filte": "1"
        },
{
"classification": "瀝青類",
          "number": "1-9",
          "productName": "鋁盆3000g",
          "size": "選購商品",
          "image": "1-9",
          "filte": "1"
        },
{
"classification": "瀝青類",
          "number": "1-10",
          "productName": "變頻式瀝青洗油機4000g",
          "size": "1.轉速約3700rpm<br>2.符合:ASTM、AASHTO規範<br>3.電源:220v/60hz/單相/馬力1hp<br> 4.防爆型馬達重量約4000kg<br>5.尺寸約50*37*55cm",
          "image": "1-10",
          "filte": "1"
        },
{
"classification": "瀝青類",
          "number": "1-11",
          "productName": "鋁盆4000g",
          "size": "選購商品",
          "image": "1-11",
          "filte": "1"
        },
{
"classification": "瀝青類",
          "number": "1-12",
          "productName": "變頻式高速離心機",
          "size": "1.符合:CNC國家認證<br>2.電源:220v/單相<br>3.馬力:1hp 防爆型馬達<br>4.重量:約50kg<br>",
          "image": "1-12",
          "filte": "1"
        },
{
"classification": "瀝青類",
          "number": "1-13",
          "productName": "新型離心杯",
          "size": "選購商品",
          "image": "1-13",
          "filte": "1"
        },
{
"classification": "瀝青類",
          "number": "1-14",
          "productName": "三公尺直尺",
          "size": "1.鋁製中空型<br>2.配件:鋁製斜度量尺x2",
          "image": "1-14",
          "filte": "1"
        },
{
"classification": "瀝青類",
          "number": "1-15",
          "productName": "三角量尺",
          "size": "選購商品",
          "image": "1-15",
          "filte": "1"
        },
{
"classification": "瀝青類",
          "number": "1-16",
          "productName": "路面平坦儀",
          "size": "1.指針式<br>2.重量約60kg",
          "image": "1-16",
          "filte": "1"
        },
{
"classification": "瀝青類",
          "number": "1-17",
          "productName": "瀝青夯實模4&quot",
          "size": "1.規格:4吋<br>2.符合CNS國家認證",
          "image": "1-17",
          "filte": "1"
        },
{
"classification": "瀝青類",
          "number": "1-18",
          "productName": "瀝青夯實模6&quot",
          "size": "1.規格:6吋<br>2.符合CNS國家認證",
          "image": "1-18",
          "filte": "1"
        },
{
"classification": "瀝青類",
          "number": "1-19",
          "productName": "瀝青夯打機 4&quot;x6&quot;兩用型&quot;",
          "size": "選購商品",
          "image": "1-19",
          "filte": "1"
        },
{
"classification": "瀝青類",
          "number": "1-20-1",
          "productName": "電動瀝青夯實機 4&quot;",
          "size": "1.規格:4吋<br>2.符合:CNS國家認證<br>3.電源:110v<br>4.馬力&quot;&frac12;hp<br>5.落距:18英吋/5.5磅",
          "image": "1-20-1",
          "filte": "1"
        },
{
"classification": "瀝青類",
          "number": "1-20-2",
          "productName": "電動夯錘 4&quot;",
          "size": "選購商品",
          "image": "1-20-2",
          "filte": "1"
        },
{
"classification": "瀝青類",
          "number": "1-21-1",
          "productName": "電動瀝青夯實機 6&quot;",
          "size": "1.規格:6吋<br>2.符合CNS國家認證<br>3.電源110v<br>4.馬力&frac12;hp<br>5.落距18英吋/10磅",
          "image": "1-21-1",
          "filte": "1"
        },
{
"classification": "瀝青類",
          "number": "1-21-2",
          "productName": "瀝青夯打基鍊條",
          "size": "選購商品",
          "image": "1-21-2",
          "filte": "1"
        },
{
"classification": "瀝青類",
          "number": "1-22",
          "productName": "電動夯錘 6&quot;",
          "size": "選購商品",
          "image": "1-22",
          "filte": "1"
        },
{
"classification": "瀝青類",
          "number": "1-23",
          "productName": "手動瀝青夯實機 4&quot;",
          "size": "1.4&quot<br>2.符合CNS國家認證",
          "image": "1-23",
          "filte": "1"
        },
{
"classification": "瀝青類",
          "number": "1-24",
          "productName": "手動夯錘 4&quot;",
          "size": "選購商品",
          "image": "1-24",
          "filte": "1"
        },
{
"classification": "瀝青類",
          "number": "1-25",
          "productName": "手動夯錘 4&quot; (含護指環)",
          "size": "選購商品",
          "image": "1-25",
          "filte": "1"
        }, 
{
"classification": "瀝青類",
          "number": "1-26",
          "productName": "手動瀝青夯實機 6&quot;",
          "size": "1.6&quot<br>2.符合CNS國家認證",
          "image": "1-26",
          "filte": "1"
        },
{
"classification": "瀝青類",
          "number": "1-27",
          "productName": "手動夯錘 6&quot;",
          "size": "選購商品",
          "image": "1-27",
          "filte": "1"
        },
{
"classification": "瀝青類",
          "number": "1-28",
          "productName": "瀝青野外透水",
          "size": "1.壓克力管容量約1000ml<br>2.重量約5kg/砝碼x1",
          "image": "1-28",
          "filte": "1"
        },
{
"classification": "瀝青類",
          "number": "1-29",
          "productName": "瀝青分樣器",
          "size": "選購商品",
          "image": "1-29",
          "filte": "1"
        },
{
"classification": "瀝青類",
          "number": "1-30",
          "productName": "瀝青手動4&quot;兩柱型",
          "size": "-",
          "image": "1-30",
          "filte": "1"
        },
{
"classification": "瀝青類",
          "number": "1-31",
          "productName": "瀝青手動頂樣器兩用型(四柱型)",
          "size": "-",
          "image": "1-31",
          "filte": "1"
        },
{
"classification": "瀝青類",
          "number": "1-32",
          "productName": "地面柏油加熱器(台車)",
          "size": "選購商品",
          "image": "1-32",
          "filte": "1"
         }
      ]
    },
    {
      "cat": "wl",
      "data": [
        {
          "classification": "混凝土類",
          "number": "2-1",
          "productName": "油壓式粗骨材搖篩機(加門加蓋)",
          "size": "1.上下震動搖篩方式、油壓式固定篩網<br>2.油壓幫浦附加安全迴路確保油壓缸不應高壓而產生故障<br>3.單一開關簡單啟動,快速洩壓可讓使用者更快取得搖篩樣式<br>4.符合CNS國家認證 <br>5.電源:110v<br>6.馬力&frac13;hp<br>7.轉速約625rpm /60hz <br>8.重量約200kg<br>9.尺寸約1050*650*750mm <br>附件:篩網 &frac32; 1 &frac34; &frac12; &frac38; #4、底盤x1",
          "image": "2-1",
          "filte": "2"
        },
{
"classification": "混凝土類",
          "number": "2-2-1",
          "productName": "油壓式粗骨材搖篩機",
          "size": "1.上下震動搖篩方式、油壓式固定篩網<br>2.油壓幫浦附加安全迴路確保油壓缸不應高壓而產生故障<br>3.單一開關簡單啟動,快速洩壓可讓使用者更快取得搖篩樣式<br>4.符合CNS國家認證 <br>5.電源:110v<br>6.馬力&frac13;hp<br>7.轉速約625rpm /60hz <br>8.重量約200kg<br>9.尺寸約1050*650*750mm <br>附件:篩網 &frac32; 1 &frac34; &frac12; &frac38; #4、底盤x1",
          "image": "2-2-1",
          "filte": "2"
        },
{
"classification": "混凝土類",
          "number": "2-2-2",
          "productName": "長方篩 (篩+框)(台製)",
          "size": "選購商品",
          "image": "2-2-2",
          "filte": "2"
        },
{
"classification": "混凝土類",
          "number": "2-2-3",
          "productName": "長方篩網(台製)",
          "size": "選購商品",
          "image": "2-2-3",
          "filte": "2"
        },
{
"classification": "混凝土類",
          "number": "2-3",
          "productName": "機械式粗骨材搖篩機",
          "size": "1.水平方式轉動、封密式降低噪音<br>2.電源:110v、220v/單相<br>3.馬力1/2hp<br>4.轉速約344rpm<br>5.重量約200kg<br>附件:篩網 &frac32; 1 &frac34; &frac12; &frac38; #4、底盤x1",
          "image": "2-3",
          "filte": "2"
        },
{
"classification": "混凝土類",
          "number": "2-4-1",
          "productName": "新型細骨材搖篩機8&quot",
          "size": "1.8英吋<br>轉速:約286rmp<br>3.打擊數約86下<br>4.電源:110v、220v/單相<br>馬力&frac13;hp直立式馬達<br> 5.重量約75kg<br>6.尺寸約900*450*750mm<br> 其他:面板60分鐘定時器、電源燈、保險絲",
          "image": "2-4-1",
          "filte": "2"
        },
{
"classification": "混凝土類",
          "number": "2-4-2",
          "productName": "數位計時搖篩機8&quot;",
          "size": "選購商品",
          "image": "2-4-2",
          "filte": "2"
        },
{
"classification": "混凝土類",
          "number": "2-5-1",
          "productName": "數位計時搖篩機12&quot;",
          "size": "選購商品",
          "image": "2-5-1",
          "filte": "2"
        },
{
"classification": "混凝土類",
          "number": "2-5-2",
          "productName": "新型細骨材搖篩機12&quot",
          "size": "1.12英吋<br>轉速:約280rmp<br>3.打擊數約79下<br>4.電源:110v、220v/單相<br>馬力&frac13;hp直立式馬達<br> 5.重量約75kg<br>6.尺寸約1000*450*750mm<br> 其他:控制系統60分鐘定時器、電源燈、保險絲(以訂購為標準)",
          "image": "2-5-2",
          "filte": "2"
        },
{
"classification": "混凝土類",
          "number": "2-6-1",
          "productName": "落杉機磨耗試驗儀",
          "size": "1.大型洩料盤700*700*60、附安全開關<br>2.符合CNS國家認證 <br>3.電源 220v/單相<br>4.馬力約1hp<br>5.轉速約30~33rpm<br>6.重量約350kg<br>7.尺寸約700*1350*1050mm<br>附件:12顆標準鋼珠、非接觸式計數器",
          "image": "2-6-1",
          "filte": "2"
        },
{
"classification": "混凝土類",
          "number": "2-6-2",
          "productName": "鋼珠(顆)",
          "size": "選購商品",
          "image": "2-6-2",
          "filte": "2"
        },
{
"classification": "混凝土類",
          "number": "2-7",
          "productName": "混凝土振動台500x500",
          "size": "-",
          "image": "2-7",
          "filte": "2"
        },
{
"classification": "混凝土類",
          "number": "2-8",
          "productName": "混凝土振動台500x500 (含變頻器)",
          "size": "-",
          "image": "2-8",
          "filte": "2"
        },
{
"classification": "混凝土類",
          "number": "2-9-1",
          "productName": "混凝土試體研磨機 (單)",
          "size": "-",
          "image": "2-9-1",
          "filte": "2"
        },
{
"classification": "混凝土類",
          "number": "2-9-2",
          "productName": "175Ø研磨盤",
          "size": "-",
          "image": "2-9-2",
          "filte": "2"
        },
{
"classification": "混凝土類",
          "number": "2-10-1",
          "productName": "混凝土試體研磨機 (雙)",
          "size": "1.鑽石螺紋研磨盤直徑約200mm x1、無段變速進刀<br>2.水冷式自動供水系統、 手動幫浦進行給油、不鏽鋼蓄水盤、不鏽鋼水罩<br>3.可手動或電動研磨、試體可磨: 15*30cm x2、10*24cm x2 10*20cm x3 7.5*15cm x3、5.5*11cm x3、5*10cm x3<br>4.符合CNS國家認證 <br>5.電源220v/三相<br>6.馬力1hp、搖擺馬力約40w、輸送馬力約25w <br>7.重量約200kg<br>8.尺寸約720*860*1060mm<br>9",
          "image": "2-10-1",
          "filte": "2"
        },
{
"classification": "混凝土類",
          "number": "2-10-2",
          "productName": "200Ø研磨盤",
          "size": "-",
          "image": "2-10-2",
          "filte": "2"
        },
{
"classification": "混凝土類",
          "number": "2-11",
          "productName": "小型震動試驗儀",
          "size": "-",
          "image": "2-11",
          "filte": "2"
        },
{
"classification": "混凝土類",
          "number": "2-12",
          "productName": "大型震動振動台 760x760",
          "size": "-",
          "image": "2-12",
          "filte": "2"
        },
{
"classification": "混凝土類",
          "number": "2-13",
          "productName": "電動搖擺器",
          "size": "-",
          "image": "2-13",
          "filte": "2"
        },
{
"classification": "混凝土類",
          "number": "2-14",
          "productName": "落沉試驗儀",
          "size": "-",
          "image": "2-14",
          "filte": "2"
        },
{
"classification": "混凝土類",
          "number": "2-15",
          "productName": "混凝土試體切割機",
          "size": "-",
          "image": "2-15",
          "filte": "2"
        },
{
"classification": "混凝土類",
          "number": "2-16",
          "productName": "水平雙軸拌合機 100L",
          "size": "-",
          "image": "2-16",
          "filte": "2"
        },
{
"classification": "混凝土類",
          "number": "2-17",
          "productName": "水平雙軸拌合機 100L (含變頻)",
          "size": "-",
          "image": "2-17",
          "filte": "2"
        },
{
"classification": "混凝土類",
          "number": "2-18",
          "productName": "岩石消散試驗儀",
          "size": "-",
          "image": "2-18",
          "filte": "2"
        },
{
"classification": "混凝土類",
          "number": "2-19",
          "productName": "小型電動水洗篩",
          "size": "-",
          "image": "2-19",
          "filte": "2"
        },
{
"classification": "混凝土類",
          "number": "2-20",
          "productName": "高性能錐型流度儀",
          "size": "-",
          "image": "2-20",
          "filte": "2"
        },
{
"classification": "混凝土類",
          "number": "2-21",
          "productName": "高性能箱型流度儀",
          "size": "-",
          "image": "2-21",
          "filte": "2"
        },
{
"classification": "混凝土類",
          "number": "2-22",
          "productName": "高性能U型流度儀",
          "size": "-",
          "image": "2-22",
          "filte": "2"
        },
{
"classification": "混凝土類",
          "number": "2-23",
          "productName": "高性能Y型流度儀",
          "size": "-",
          "image": "2-23",
          "filte": "2"
        },
{
"classification": "混凝土類",
          "number": "2-24",
          "productName": "水泥砂漿流度錐",
          "size": "-",
          "image": "2-24",
          "filte": "2"
        },
{
"classification": "混凝土類",
          "number": "2-25-1",
          "productName": "SCC高性能坍度板 不鏽鋼",
          "size": "-",
          "image": "2-25-1",
          "filte": "2"
        },
{
"classification": "混凝土類",
          "number": "2-25-2",
          "productName": "800x800x3mm 含調整腳",
          "size": "-",
          "image": "2-25-2",
          "filte": "2"
        },
{
"classification": "混凝土類",
          "number": "2-26",
          "productName": "電動水泥砂漿流度台",
          "size": "-",
          "image": "2-26",
          "filte": "2"
        },
{
"classification": "混凝土類",
          "number": "2-27-1",
          "productName": "手動水泥砂漿流度台",
          "size": "-",
          "image": "2-27-1",
          "filte": "2"
        },
{
"classification": "混凝土類",
          "number": "2-27-2",
          "productName": "流度台椎模",
          "size": "-",
          "image": "2-27-2",
          "filte": "2"
        },
{
"classification": "混凝土類",
          "number": "2-28",
          "productName": "混凝土透水試驗儀",
          "size": "-",
          "image": "2-28",
          "filte": "2"
        },
{
"classification": "混凝土類",
          "number": "2-29-1",
          "productName": "維克針入儀",
          "size": "-",
          "image": "2-29-1",
          "filte": "2"
        },
{
"classification": "混凝土類",
          "number": "2-29-2",
          "productName": "維克針銅模",
          "size": "-",
          "image": "2-29-2",
          "filte": "2"
        },
{
"classification": "混凝土類",
          "number": "2-30",
          "productName": "吉爾模",
          "size": "-",
          "image": "2-30",
          "filte": "2"
        },
{
"classification": "混凝土類",
          "number": "2-31",
          "productName": "劈裂模15x30cm",
          "size": "-",
          "image": "2-31",
          "filte": "2"
        },
{
"classification": "混凝土類",
          "number": "2-32",
          "productName": "鄂碎機",
          "size": "-",
          "image": "2-32",
          "filte": "2"
        },
{
"classification": "混凝土類",
          "number": "2-33",
          "productName": "砂表干",
          "size": "-",
          "image": "2-33",
          "filte": "2"
        },
{
"classification": "混凝土類",
          "number": "2-34",
          "productName": "八字模",
          "size": "-",
          "image": "2-34",
          "filte": "2"
        },
{
"classification": "混凝土類",
          "number": "2-35",
          "productName": "扁平規",
          "size": "-",
          "image": "2-35",
          "filte": "2"
        },
{
"classification": "混凝土類",
          "number": "2-36",
          "productName": "混凝土油壓式貫入儀",
          "size": "-",
          "image": "2-36",
          "filte": "2"
        },
{
"classification": "混凝土類",
          "number": "2-37",
          "productName": "混凝土電子式貫入儀",
          "size": "-",
          "image": "2-37",
          "filte": "2"
        },
{
"classification": "混凝土類",
          "number": "2-38",
          "productName": "衝擊試驗儀",
          "size": "-",
          "image": "2-38",
          "filte": "2"
        },
{
"classification": "混凝土類",
          "number": "2-39",
          "productName": "長度比較儀",
          "size": "-",
          "image": "2-39",
          "filte": "2"
        },
{
"classification": "混凝土類",
          "number": "2-40",
          "productName": "小型抗壓承座",
          "size": "-",
          "image": "2-40",
          "filte": "2"
        },
{
"classification": "混凝土類",
          "number": "2-41",
          "productName": "砂漿模 (鋁製)",
          "size": "-",
          "image": "2-41",
          "filte": "2"
        },
{
"classification": "混凝土類",
          "number": "2-42",
          "productName": "4x4x16抗彎模",
          "size": "-",
          "image": "2-42",
          "filte": "2"
        },
{
"classification": "混凝土類",
          "number": "2-43",
          "productName": "厚薄校正台",
          "size": "-",
          "image": "2-43",
          "filte": "2"
        },
{
"classification": "混凝土類",
          "number": "2-44",
          "productName": "升降式比重桌",
          "size": "-",
          "image": "2-44",
          "filte": "2"
        },
{
"classification": "混凝土類",
          "number": "2-45",
          "productName": "大型電動水洗篩",
          "size": "-",
          "image": "2-45",
          "filte": "2"
        },
{
"classification": "混凝土類",
          "number": "2-46",
          "productName": "電極試驗儀 (壓克力室)",
          "size": "-",
          "image": "2-46",
          "filte": "2"
        },
{
"classification": "混凝土類",
          "number": "2-47",
          "productName": "大型腰樑鐵模",
          "size": "-",
          "image": "2-47",
          "filte": "2"
        },
{
"classification": "混凝土類",
          "number": "2-48",
          "productName": "水中磨耗試驗儀",
          "size": "-",
          "image": "2-48",
          "filte": "2"
        },
{
"classification": "混凝土類",
          "number": "2-49",
          "productName": "粉末磨耗試驗儀",
          "size": "-",
          "image": "2-49",
          "filte": "2"
        },
{
"classification": "混凝土類",
          "number": "2-50",
          "productName": "三等分點",
          "size": "-",
          "image": "2-50",
          "filte": "2"
        },
{
"classification": "混凝土類",
          "number": "2-51",
          "productName": "潛變",
          "size": "-",
          "image": "2-51",
          "filte": "2"
        },
{
"classification": "混凝土類",
          "number": "2-52",
          "productName": "抗壓機墊塊 165Øx60mm",
          "size": "-",
          "image": "2-52",
          "filte": "2"
        },
{
"classification": "混凝土類",
          "number": "2-53",
          "productName": "噴砂機",
          "size": "-",
          "image": "2-53",
          "filte": "2"
        },
{
"classification": "混凝土類",
          "number": "2-54",
          "productName": "膨脹模 25*25*285(二聯式)",
          "size": "-",
          "image": "2-54",
          "filte": "2"
        },
{
"classification": "混凝土類",
          "number": "2-55",
          "productName": "膨脹模 25*25*285(三聯式)",
          "size": "-",
          "image": "2-55",
          "filte": "2"
        },
{
"classification": "混凝土類",
          "number": "2-56",
          "productName": "膨脹模 75*75*285(二聯式)",
          "size": "-",
          "image": "2-56",
          "filte": "2"
        },
{
"classification": "混凝土類",
          "number": "2-57",
          "productName": "不鏽鋼螺絲316(顆)",
          "size": "-",
          "image": "2-57",
          "filte": "2"
        },
{
"classification": "混凝土類",
          "number": "2-58",
          "productName": "800*800*2mm度鋅鈑",
          "size": "-",
          "image": "2-58",
          "filte": "2"
        },
{
"classification": "混凝土類",
          "number": "2-59",
          "productName": "500*500*2mm度鋅鈑",
          "size": "-",
          "image": "2-59",
          "filte": "2"
        },
{
"classification": "混凝土類",
          "number": "2-60",
          "productName": "電動水洗機",
          "size": "-",
          "image": "2-60",
          "filte": "2"
        },
{
"classification": "混凝土類",
          "number": "2-61",
          "productName": "衝擊測試儀",
          "size": "-",
          "image": "2-61",
          "filte": "2"
        },
{
"classification": "混凝土類",
          "number": "2-62-1",
          "productName": "單位重量桶 3L",
          "size": "選購商品",
          "image": "2-62-1",
          "filte": "2"
        },
{
"classification": "混凝土類",
          "number": "2-62-2",
          "productName": "單位重量桶 10L",
          "size": "選購商品",
          "image": "2-62-2",
          "filte": "2"
        },
{
"classification": "混凝土類",
          "number": "2-62-3",
          "productName": "單位重量桶 15L",
          "size": "選購商品",
          "image": "2-62-3",
          "filte": "2"
        },
{
"classification": "混凝土類",
          "number": "2-62-4",
          "productName": "單位重量桶 30L",
          "size": "選購商品",
          "image": "2-62-4",
          "filte": "2"
        },
{
"classification": "混凝土類",
          "number": "2-63",
          "productName": "校正桶",
          "size": "-",
          "image": "2-63",
          "filte": "2"
          }
      ]
    },

    {
      "cat": "tl",
      "data": [
        {"classification": "土壤類",
          "number": "3-1",
          "productName": "土壤夯實機(新電腦設定型)",
          "size": "-",
          "image": "3-1",
          "filte": "3"
        },
{
"classification": "土壤類",
          "number": "3-2",
          "productName": "電動頂樣器(油壓式)",
          "size": "-",
          "image": "3-2",
          "filte": "3"
        },
{
"classification": "土壤類",
          "number": "3-3",
          "productName": "手動頂樣器(四柱型)",
          "size": "-",
          "image": "3-3",
          "filte": "3"
        },
{
"classification": "土壤類",
          "number": "3-4",
          "productName": "多功能抗壓試驗儀",
          "size": "-",
          "image": "3-4",
          "filte": "3"
        },
{
"classification": "土壤類",
          "number": "3-5",
          "productName": "單軸試驗儀",
          "size": "-",
          "image": "3-5",
          "filte": "3"
        },
{
"classification": "土壤類",
          "number": "3-6",
          "productName": "定水頭變水頭(單聯)",
          "size": "-",
          "image": "3-6",
          "filte": "3"
        },
{
"classification": "土壤類",
          "number": "3-7",
          "productName": "土壤相對密度",
          "size": "-",
          "image": "3-7",
          "filte": "3"
        },
{
"classification": "土壤類",
          "number": "3-8",
          "productName": "土壤相對密度(模具)",
          "size": "-",
          "image": "3-8",
          "filte": "3"
        },
{
"classification": "土壤類",
          "number": "3-9",
          "productName": "油壓薄管頂樣器",
          "size": "-",
          "image": "3-9",
          "filte": "3"
        },
{
"classification": "土壤類",
          "number": "3-10",
          "productName": "直接剪力試驗儀",
          "size": "-",
          "image": "3-10",
          "filte": "3"
        },
{
"classification": "土壤類",
          "number": "3-11",
          "productName": "數位式直接剪力試驗儀",
          "size": "-",
          "image": "3-11",
          "filte": "3"
        },
{
"classification": "土壤類",
          "number": "3-12",
          "productName": "土壤夯模 4&quot",
          "size": "-",
          "image": "3-12",
          "filte": "3"
        },
{
"classification": "土壤類",
          "number": "3-13",
          "productName": "土壤夯模 6&quot",
          "size": "-",
          "image": "3-13",
          "filte": "3"
        },
{
"classification": "土壤類",
          "number": "3-14",
          "productName": "CBR試驗儀",
          "size": "-",
          "image": "3-14",
          "filte": "3"
        },
{
"classification": "土壤類",
          "number": "3-15",
          "productName": "CBR模",
          "size": "-",
          "image": "3-15",
          "filte": "3"
        },
{
"classification": "土壤類",
          "number": "3-16",
          "productName": "鉛馬蹄型",
          "size": "-",
          "image": "3-16",
          "filte": "3"
        },
{
"classification": "土壤類",
          "number": "3-17",
          "productName": "鉛圓型",
          "size": "-",
          "image": "3-17",
          "filte": "3"
        },
{
"classification": "土壤類",
          "number": "3-18",
          "productName": "鉛半圓型",
          "size": "-",
          "image": "3-18",
          "filte": "3"
        },
{
"classification": "土壤類",
          "number": "3-19",
          "productName": "膨脹頂扳",
          "size": "-",
          "image": "3-19",
          "filte": "3"
        },
{
"classification": "土壤類",
          "number": "3-20",
          "productName": "三角架",
          "size": "-",
          "image": "3-20",
          "filte": "3"
        },
{
"classification": "土壤類",
          "number": "3-21",
          "productName": "墊塊",
          "size": "-",
          "image": "3-21",
          "filte": "3"
        },
{
"classification": "土壤類",
          "number": "3-22",
          "productName": "刮刀",
          "size": "-",
          "image": "3-22",
          "filte": "3"
        },
{
"classification": "土壤類",
          "number": "3-23",
          "productName": "土壤夯錘 5.5磅",
          "size": "-",
          "image": "3-23",
          "filte": "3"
        },
{
"classification": "土壤類",
          "number": "3-24",
          "productName": "土壤夯錘 10磅",
          "size": "-",
          "image": "3-24",
          "filte": "3"
        },
{
"classification": "土壤類",
          "number": "3-25-1",
          "productName": "壓密",
          "size": "-",
          "image": "3-25-1",
          "filte": "3"
        },
{
"classification": "土壤類",
          "number": "3-25-2",
          "productName": "壓密合(室)",
          "size": "-",
          "image": "3-25-2",
          "filte": "3"
        },
{
"classification": "土壤類",
          "number": "3-26",
          "productName": "擁壁試驗儀",
          "size": "-",
          "image": "3-26",
          "filte": "3"
        },
{
"classification": "土壤類",
          "number": "3-27",
          "productName": "基礎的支持力試驗儀",
          "size": "-",
          "image": "3-27",
          "filte": "3"
        },
{
"classification": "土壤類",
          "number": "3-28",
          "productName": "岩心管切割機",
          "size": "-",
          "image": "3-28",
          "filte": "3"
        },
{
"classification": "土壤類",
          "number": "3-29",
          "productName": "變頻式水頻震動台",
          "size": "-",
          "image": "3-29",
          "filte": "3"
        },
{
"classification": "土壤類",
          "number": "3-30",
          "productName": "土壤透水",
          "size": "-",
          "image": "3-30",
          "filte": "3"
            }
      ]
    },
    {
      "cat": "ji",
      "data": [

        {"classification": "金相類",
          "number": "4-1",
          "productName": "雙盤式研磨拋光機",
          "size": "-",
          "image": "4-1",
          "filte": "4"
        },
{
"classification": "金相類",
          "number": "4-2",
          "productName": "岩石切磨機",
          "size": "-",
          "image": "4-2",
          "filte": "4"
        },
{
"classification": "金相類",
          "number": "4-3",
          "productName": "金相切割機 (35型)",
          "size": "-",
          "image": "4-3",
          "filte": "4"
        },
{
"classification": "其他",
          "number": "5-1",
          "productName": "落下試驗儀",
          "size": "客製商品",
          "image": "5-1",
          "filte": "5"
        },
{
"classification": "其他",
          "number": "5-2",
          "productName": "拉力試驗儀",
          "size": "客製商品",
          "image": "5-2",
          "filte": "5"
        },
{
"classification": "其他",
          "number": "5-3",
          "productName": "紙箱壓力機",
          "size": "客製商品",
          "image": "5-3",
          "filte": "5"
        },
{
"classification": "其他",
          "number": "5-4",
          "productName": "岩石直剪試驗儀",
          "size": "客製商品",
          "image": "5-4",
          "filte": "5"
                }
      ]
    }
  ]
}
